freesas/dnn.py
freesas/_cormap.cpython-311-darwin.so
freesas/plot.py
freesas/version.py
freesas/align.py
freesas/transformations.py
freesas/containers.py
freesas/autorg.py
freesas/__init__.py
freesas/_bift.cpython-311-darwin.so
freesas/cormap.py
freesas/model.py
freesas/_distance.cpython-311-darwin.so
freesas/fitting.py
freesas/sas_argparser.py
freesas/bift.py
freesas/average.py
freesas/sasio.py
freesas/invariants.py
freesas/_autorg.cpython-311-darwin.so
freesas/decorators.py
freesas/app/dnn.py
freesas/app/auto_guinier.py
freesas/app/plot_sas.py
freesas/app/autorg.py
freesas/app/__init__.py
freesas/app/cormap.py
freesas/app/supycomb.py
freesas/app/extract_ascii.py
freesas/app/auto_gpa.py
freesas/app/bift.py
freesas/test/test_cormap.py
freesas/test/utilstest.py
freesas/test/test_resources.py
freesas/test/test_model.py
freesas/test/mock_open_38.py
freesas/test/test_all.py
freesas/test/test_distance.py
freesas/test/test_dnn.py
freesas/test/__init__.py
freesas/test/test_sasio.py
freesas/test/test_fitting.py
freesas/test/test_align.py
freesas/test/test_autorg.py
freesas/test/test_bift.py
freesas/test/test_sas_argparser.py
freesas/test/test_average.py
freesas/resources/__init__.py
freesas/resources/keras_models/Rg+Dmax.keras
freesas-2024.9.0.dist-info/RECORD
freesas-2024.9.0.dist-info/WHEEL
freesas-2024.9.0.dist-info/entry_points.txt
freesas-2024.9.0.dist-info/copyright
freesas-2024.9.0.dist-info/METADATA
