Metadata-Version: 2.1
Name: freesas
Version: 2024.9.0
Summary: Small angle scattering tools ... but unlike most others, free and written in Python
Home-page: http://silx.org
Author: Guillaume Bonamis, Martha Brennich
Author-Email: =?utf-8?b?SsODwqlyw4PCtG1lIEtpZWZmZXI=?= <jerome.kieffer@esrf.fr>
License: Format: http://www.debian.org/doc/packaging-manuals/copyright-format/1.0/
Classifier: Development Status :: 5 - Production/Stable
Classifier: Environment :: Console
Classifier: Intended Audience :: Developers
Classifier: Intended Audience :: Education
Classifier: Intended Audience :: Science/Research
Classifier: License :: OSI Approved :: MIT License
Classifier: Natural Language :: English
Classifier: Operating System :: MacOS :: MacOS X
Classifier: Operating System :: Microsoft :: Windows
Classifier: Operating System :: Unix
Classifier: Operating System :: POSIX
Classifier: Programming Language :: Cython
Classifier: Programming Language :: Python :: 3
Classifier: Programming Language :: Python :: Implementation :: CPython
Classifier: Topic :: Scientific/Engineering :: Physics
Classifier: Topic :: Software Development :: Libraries :: Python Modules
Classifier: Topic :: Scientific/Engineering :: Bio-Informatics
Project-URL: Homepage, http://silx.org
Project-URL: Documentation, http://www.silx.org/doc/freesas/latest/
Project-URL: Source, https://github.com/silx-kit/freeas
Project-URL: Download, https://github.com/silx-kit/freesas/releases
Project-URL: Tracker, https://github.com/silx-kit/freesas/issues
Requires-Python: >=3.7
Requires-Dist: numpy
Requires-Dist: scipy
Requires-Dist: matplotlib
Requires-Dist: silx
